README.rst
setup.py
Chronologer.egg-info/PKG-INFO
Chronologer.egg-info/SOURCES.txt
Chronologer.egg-info/dependency_links.txt
Chronologer.egg-info/requires.txt
Chronologer.egg-info/top_level.txt
chronologer/__init__.py
chronologer/__main__.py
chronologer/cli.py
chronologer/client.py
chronologer/envconf.py
chronologer/model.py
chronologer/server.py
chronologer/utility.py
chronologer/controller/__init__.py
chronologer/controller/auth.py
chronologer/controller/toolbox.py
chronologer/migration/mysql/20171026T1428_initial.py
chronologer/migration/sqlite/20181110T1614_initial.py
chronologer/migration/sqlite/post-apply.py
chronologer/storage/__init__.py
chronologer/storage/mysql.py
chronologer/storage/sqlite.py
chronologer/test/__init__.py
chronologer/test/client.py
chronologer/test/controller.py
chronologer/test/model.py
chronologer/test/storage/__init__.py
chronologer/test/storage/mysql.py
chronologer/test/storage/sqlite.py