Metadata-Version: 2.1
Name: Chronologer
Version: 0.4.4
Summary: Python HTTP logging server
Home-page: https://heptapod.host/saajns/chronologer/tree/branch/backend
Author: saaj
Author-email: mail@saaj.me
License: GPL-3.0
Keywords: python logging http json
Platform: Any
Classifier: Topic :: Database
Classifier: Framework :: CherryPy
Classifier: Programming Language :: Python :: 3
Classifier: Programming Language :: Python :: 3 :: Only
Classifier: Programming Language :: Python :: 3.5
Classifier: Programming Language :: Python :: 3.6
Classifier: Programming Language :: Python :: 3.7
Classifier: Programming Language :: Python :: Implementation :: CPython
Classifier: Intended Audience :: Developers
Provides-Extra: ui
Provides-Extra: server
Provides-Extra: mysql
